sorl_thumbnail_avif/__init__.py
sorl_thumbnail_avif/thumbnail/__init__.py
sorl_thumbnail_avif/thumbnail/base.py
sorl_thumbnail_avif/thumbnail/engines/__init__.py
sorl_thumbnail_avif/thumbnail/engines/pil_engine.py
sorl_thumbnail_avif-0.1.0.post1.dist-info/METADATA
sorl_thumbnail_avif-0.1.0.post1.dist-info/WHEEL
sorl_thumbnail_avif-0.1.0.post1.dist-info/RECORD
